Metadata-Version: 2.1
Name: distributionsFinal
Version: 0.1
Summary: Gaussian and Binomial distributions
Home-page: UNKNOWN
License: UNKNOWN
Platform: UNKNOWN
License-File: license.txt
